macrotools/__init__.py
macrotools/pull_data.py
macrotools/storage.py
macrotools/time_series.py
macrotools/time_series_graph.py
macrotools/utils.py
macrotools/data/pceseries.csv
macrotools/styles/eastyle.mplstyle
macrotools/styles/fonts/Montserrat-Regular.ttf
macrotools-0.1.3.dist-info/licenses/LICENSE
macrotools-0.1.3.dist-info/METADATA
macrotools-0.1.3.dist-info/WHEEL
macrotools-0.1.3.dist-info/top_level.txt
macrotools-0.1.3.dist-info/RECORD
