Metadata-Version: 2.4
Name: macrotools
Version: 0.1.3
Summary: Employ America tools for pulling and graphing U.S. macroeconomic data.
Author-email: Preston Mui <preston@employamerica.org>
Requires-Python: >=3.9
License-File: LICENSE
Requires-Dist: matplotlib>=3.10.0
Requires-Dist: numpy>=2.0.0
Requires-Dist: statsmodels>=0.14.4
Requires-Dist: pandas>=2.2.3
Requires-Dist: requests>=2.32.3
Dynamic: license-file
